midi2cmd/__init__.py
midi2cmd/console.py
midi2cmd/midi_reader.py
midi2cmd-0.1.0.dist-info/METADATA
midi2cmd-0.1.0.dist-info/WHEEL
midi2cmd-0.1.0.dist-info/entry_points.txt
midi2cmd-0.1.0.dist-info/RECORD
